youtube_stream/__init__.py
youtube_stream/__main__.py
youtube_stream/ascii_art.txt
youtube_stream/commands.py
youtube_stream/config.txt
youtube_stream/distrun.py
youtube_stream/imports.py
youtube_stream/mute_shell.py
youtube_stream/playmedia.py
youtube_stream/search.py
youtube_stream/voice_recognition.py
youtube_stream/windows.png
youtube_stream-0.0.14.dist-info/LICENSE.txt
youtube_stream-0.0.14.dist-info/METADATA
youtube_stream-0.0.14.dist-info/WHEEL
youtube_stream-0.0.14.dist-info/entry_points.txt
youtube_stream-0.0.14.dist-info/top_level.txt
youtube_stream-0.0.14.dist-info/RECORD
