Metadata-Version: 2.1
Name: youtube-stream
Version: 0.0.14
Summary: Stream Youtube Music Videos from Command Line!
Home-page: https://github.com/sanjib-sen/youtube-stream
Author: Sanjib Kumar Sen
Author-email: sksenonline@gmail.com
License: MIT
Download-URL: https://github.com/sanjib-sen/youtube-stream/archive/v_0.0.14.tar.gz
Keywords: youtube,streaming,vlc,video,audio,automation
Platform: UNKNOWN
Classifier: Development Status :: 4 - Beta
Classifier: License :: OSI Approved :: MIT License
Classifier: Programming Language :: Python :: 3
Classifier: Programming Language :: Python :: 3.9
Classifier: Intended Audience :: End Users/Desktop
Classifier: Natural Language :: English
Classifier: Operating System :: OS Independent
Classifier: Topic :: Home Automation
Classifier: Topic :: Multimedia :: Video :: Display
License-File: LICENSE.txt
Requires-Dist: SpeechRecognition
